airouter/__init__.py
airouter/chat.py
airouter/completions.py
airouter/router.py
airouter/types.py
airouter_sdk-0.2.6.dist-info/LICENSE
airouter_sdk-0.2.6.dist-info/METADATA
airouter_sdk-0.2.6.dist-info/WHEEL
airouter_sdk-0.2.6.dist-info/RECORD
