Metadata-Version: 2.1
Name: airouter-sdk
Version: 0.2.6
Summary: Official Python SDK for airouter.io - Automatically route requests to the best Large Language Model (LLM).
Home-page: https://github.com/heureka-labs/ai-router-sdk
License: MIT
Requires-Python: >=3.11,<3.13
Classifier: License :: OSI Approved :: MIT License
Classifier: Programming Language :: Python :: 3
Classifier: Programming Language :: Python :: 3.11
Classifier: Programming Language :: Python :: 3.12
Provides-Extra: privacy
Requires-Dist: fastembed (>=0.4.2,<0.5.0) ; extra == "privacy"
Requires-Dist: openai (>=1.57.0,<2.0.0)
Project-URL: Repository, https://github.com/heureka-labs/ai-router-sdk
